aman_llm/__init__.py
aman_llm/llm.py
aman_llm/utils.py
aman_llm-0.1.6.dist-info/METADATA
aman_llm-0.1.6.dist-info/WHEEL
aman_llm-0.1.6.dist-info/top_level.txt
aman_llm-0.1.6.dist-info/RECORD
